uol_auto_vpn/__init__.py
uol_auto_vpn/credentials.py
uol_auto_vpn/driver.py
uol_auto_vpn/env.py
uol_auto_vpn/experimental.py
uol_auto_vpn/run.py
uol_auto_vpn/version.py
uol_auto_vpn-1.0.3.dist-info/LICENSE
uol_auto_vpn-1.0.3.dist-info/METADATA
uol_auto_vpn-1.0.3.dist-info/WHEEL
uol_auto_vpn-1.0.3.dist-info/entry_points.txt
uol_auto_vpn-1.0.3.dist-info/top_level.txt
uol_auto_vpn-1.0.3.dist-info/RECORD
