Metadata-Version: 2.1
Name: uol-auto-vpn
Version: 1.0.3
Summary: Auto connect to UoL VPN by Raymond Tunstill.
Home-page: https://raymondkirk.github.io/uol_auto_vpn/
Author: Raymond Tunstill
Author-email: ray.tunstill@gmail.com
License: GNU GPLv3
Platform: UNKNOWN
Classifier: Programming Language :: Python :: 3
Requires-Python: >=3.6
License-File: LICENSE
Requires-Dist: selenium (==3.141.0)
Requires-Dist: keyring (==23.2.1)
